SAInT/__init__.py
SAInT/__main__.py
SAInT/common.py
SAInT/data_augmentation.py
SAInT/data_balancer.py
SAInT/data_normalizer.py
SAInT/data_settings copy.py
SAInT/data_settings.py
SAInT/data_visualizer.py
SAInT/dataloader copy 2.py
SAInT/dataloader copy.py
SAInT/dataloader.py
SAInT/dataset copy.py
SAInT/dataset.py
SAInT/metric.py
SAInT/model.py
SAInT/modelloader.py
SAInT/online_normalization.py
SAInT/piep.py
SAInT/read_floarian_rf.py
SAInT/run_dash_application.py
SAInT/run_optimizer_application.py
SAInT/trainer.py
SAInT/update_florian_models.py
SAInT/dash_application/__init__.py
SAInT/dash_application/dash_component.py
SAInT/dash_application/logo.svg
SAInT/dash_application/optimizer_application.py
SAInT/dash_application/optimizer_dash_app copy.py
SAInT/dash_application/optimizer_dash_app.py
SAInT/dash_application/optimizer_dash_layout_components.py
SAInT/dash_application/piep.py
SAInT/dash_application/pixel_definitions copy.py
SAInT/dash_application/pixel_definitions copy1.py
SAInT/dash_application/pixel_definitions.py
SAInT/dash_application/saint_application.py
SAInT/dash_application/saint_dash_app.py
SAInT/dash_application/saint_dash_layout_components.py
SAInT/dash_application/assets/confirm_dialog_style.js
SAInT/dash_application/assets/custom.css
SAInT/dash_application/assets/custom_error.js
SAInT/dash_application/assets/custom_reload_warning.js
SAInT/dash_application/callbacks/__init__.py
SAInT/dash_application/callbacks/add_model_callback.py
SAInT/dash_application/callbacks/apply_adaptation_callback.py
SAInT/dash_application/callbacks/automatic_callback.py
SAInT/dash_application/callbacks/console_callback.py
SAInT/dash_application/callbacks/create_optimizer_callback.py
SAInT/dash_application/callbacks/data_callback copy.py
SAInT/dash_application/callbacks/data_callback.py
SAInT/dash_application/callbacks/data_callback2.py
SAInT/dash_application/callbacks/data_callbackooo.py
SAInT/dash_application/callbacks/feature_selection_popup_callback.py
SAInTool-1.1.5.dist-info/METADATA
SAInTool-1.1.5.dist-info/WHEEL
SAInTool-1.1.5.dist-info/top_level.txt
SAInTool-1.1.5.dist-info/RECORD
