Metadata-Version: 2.1
Name: SAInTool
Version: 1.1.5
Summary: SAInT: An Interactive Tool for Sensitivity Analysis In The Loop
Home-page: https://github.com/dfki-asr/c3di/SAInT
Author: Manuela Schuler
Author-email: Manuela.Schuler@dfki.de
License: MIT
Project-URL: Source, https://github.com/dfki-asr/c3di/SAInT
Platform: any
Classifier: Development Status :: 4 - Beta
Classifier: Programming Language :: Python :: 3
Requires-Dist: numpy==1.26.4
Requires-Dist: numba==0.59.1
Requires-Dist: torch==2.2.0
Requires-Dist: torchvision==0.17.0
Requires-Dist: fastai==2.7.16
Requires-Dist: matplotlib>=3.9.2
Requires-Dist: pandas==2.2.2
Requires-Dist: seaborn==0.13.2
Requires-Dist: scikit-learn==1.5.1
Requires-Dist: typing>=3.7.4.3
Requires-Dist: joblib>=1.4.2
Requires-Dist: SALib==1.5.1
Requires-Dist: lime==0.2.0.1
Requires-Dist: xgboost==2.1.1
Requires-Dist: shap==0.46.0
Requires-Dist: dash==2.18.1
Requires-Dist: dash-bootstrap-components==1.6.0
Requires-Dist: kaleido>=0.2.1
Requires-Dist: ipython==8.26.0
Requires-Dist: ipykernel==6.29.4
Requires-Dist: setuptools>=74.1.1
Provides-Extra: testing
Requires-Dist: setuptools; extra == "testing"
Requires-Dist: pytest; extra == "testing"
Requires-Dist: pytest-cov; extra == "testing"
